invalid_info/__init__.py
invalid_info/aadhar.py
invalid_info/family.py
invalid_info/ifsc.py
invalid_info/instagram.py
invalid_info/ip.py
invalid_info/mobile.py
invalid_info/pin.py
invalid_info/song.py
invalid_info/vehicle.py
invalid_info-1.0.0.dist-info/METADATA
invalid_info-1.0.0.dist-info/WHEEL
invalid_info-1.0.0.dist-info/top_level.txt
invalid_info-1.0.0.dist-info/RECORD
