Metadata-Version: 2.4
Name: invalid_info
Version: 1.0.0
Summary: Multi-purpose info fetching package
Author: Invalid Ayush
Author-email: invalid.ayush@example.com
Requires-Python: >=3.8
Requires-Dist: requests
Requires-Dist: instaloader
Dynamic: author
Dynamic: author-email
Dynamic: requires-dist
Dynamic: requires-python
Dynamic: summary
